xhs_mcp/__init__.py
xhs_mcp/__main__.py
xhs_mcp/client.py
xhs_mcp/config.py
xhs_mcp/server.py
xhs_mcp_fy-0.1.2.dist-info/METADATA
xhs_mcp_fy-0.1.2.dist-info/WHEEL
xhs_mcp_fy-0.1.2.dist-info/entry_points.txt
xhs_mcp_fy-0.1.2.dist-info/licenses/LICENSE
xhs_mcp_fy-0.1.2.dist-info/RECORD
