Metadata-Version: 2.4
Name: xhs-mcp-fy
Version: 0.1.2
Summary: A Model Context Protocol server for accessing Xiaohongshu (Little Red Book) content
Author-email: fuyou <imshuazi@126.com>
License-File: LICENSE
Requires-Python: >=3.10
Requires-Dist: httpx>=0.27.0
Requires-Dist: mcp[cli]>=1.0.0
Requires-Dist: xhshow>=0.1.0
Provides-Extra: dev
Requires-Dist: commitizen>=3.0.0; extra == 'dev'
Requires-Dist: pre-commit>=3.0.0; extra == 'dev'
Requires-Dist: pytest-asyncio>=0.23.0; extra == 'dev'
Requires-Dist: pytest-cov>=4.1.0; extra == 'dev'
Requires-Dist: pytest>=8.0.0; extra == 'dev'
Requires-Dist: ruff>=0.13.2; extra == 'dev'
